{
  "project_info": {
    "project_number": "722942875039",
    "firebase_url": "https://storevue.firebaseio.com",
    "project_id": "storevue",
    "storage_bucket": "storevue.appspot.com"
  },
  "client": [
    {
      "client_info": {
        "mobilesdk_app_id": "1:722942875039:android:a8f82c20b04e485bf899aa",
        "android_client_info": {
          "package_name": "com.lookstore"
        }
      },
      "oauth_client": [
        {
          "client_id": "722942875039-t53omcrhiqk5cq0illvliiibvrhh1gal.apps.googleusercontent.com",
          "client_type": 3
        }
      ],
      "api_key": [
        {
          "current_key": "AIzaSyDzmZ7ZU2up2IxGTtG8vKZGx4C7jvOr2D4"
        }
      ],
      "services": {
        "appinvite_service": {
          "other_platform_oauth_client": [
            {
              "client_id": "722942875039-t53omcrhiqk5cq0illvliiibvrhh1gal.apps.googleusercontent.com",
              "client_type": 3
            },
            {
              "client_id": "722942875039-5fhhhi6ek13b0ajd4p1681v8hqtck6ud.apps.googleusercontent.com",
              "client_type": 2,
              "ios_info": {
                "bundle_id": "com.adv.storeviu.StoreMo"
              }
            }
          ]
        }
      }
    }
  ],
  "configuration_version": "1"
}